Monocycle/Verilog/Código/register_file.sv
module register_file(
    input wire clk,
  	input wire [4:0] rs1,   
  	input wire [4:0] rs2, 
  	input wire [4:0] rd,   
    input wire RUWr,
  	input wire [31:0] DataWr,
  	output wire [31:0] RU_rs1,
  	output wire [31:0] RU_rs2
);
    
  	reg [31:0] memory [31:0];
    
    initial begin
      for (int i=0; i<32; i=i+1) begin
            memory[i] = 32'h0;
        end
      memory[1] = 32'h0068;
      memory[2] = 32'd1024;
    end
    
    always @(posedge clk) begin
      if (RUWr == 1'b1 && rd != 5'b00000)
        begin
          memory[rd] <= DataWr;
        end
    end
    
  	assign RU_rs1 = memory[rs1];
  	assign RU_rs2 = memory[rs2];
    
endmodule

Monocycle/Verilog/Código/branch_unit.sv
module branch_unit (
    input wire [4:0] BrOp, 
    input wire [31:0] A,
    input wire [31:0] B, 
    output reg NextPCSrc  
);
   always @(*) begin
        if (BrOp[4] == 1'b1) begin
            NextPCSrc = 1'b1;
        end else begin
            if(BrOp[4:3] == 2'b0) begin
                NextPCSrc = 1'b0;
            end else begin
                case (BrOp)
                    5'b01000: NextPCSrc = (A == B);
                    5'b01001: NextPCSrc = (A != B);
                    5'b01100: NextPCSrc = ($signed(A) < $signed(B));
                    5'b01101: NextPCSrc = ($signed(A) >= $signed(B));
                    5'b01110: NextPCSrc = (A < B);
                    5'b01111: NextPCSrc = (A >= B);
                    default: NextPCSrc = 0;
                endcase
            end
        end
    end

endmodule

Monocycle/Verilog/Código/data_memory.sv
module data_memory(
  	input wire clk,
    input wire DMWr,            
    input wire [2:0] DMCtrl,
    input wire [31:0] addr,  
    input wire [31:0] DataWr,
    output reg [31:0] DataRd 
);
  reg [31:0] mem [1023:0];
  
  	initial begin
    	DataRd = 32'h0;
    end
  
     always @(*) begin
        case (DMCtrl)
            3'b000: DataRd <= {{24{mem[addr[11:2]][7]}}, mem[addr[11:2]][7:0]};    // Byte
            3'b001: DataRd <= {{16{mem[addr[11:2]][15]}}, mem[addr[11:2]][15:0]};  // Halfword
            3'b010: DataRd <= mem[addr[11:2]];                               // Word
            3'b100: DataRd <= {24'b0, mem[addr[11:2]][7:0]};                 // Byte Unsigned
            3'b101: DataRd <= {16'b0, mem[addr[11:2]][15:0]};                // Halfword Unsigned
        endcase
        
    end

    always_ff @(posedge clk) begin
        if(DMWr) begin
            case (DMCtrl)
                3'b000: mem[addr[11:2]] <= {{24{DataWr[7]}}, DataWr[7:0]};    // Byte
                3'b001: mem[addr[11:2]] <= {{16{DataWr[15]}}, DataWr[15:0]};  // Halfword
                3'b010: mem[addr[11:2]] <= DataWr;                               // Word
                3'b100: mem[addr[11:2]] <= {24'b0, DataWr[7:0]};                 // Byte Unsigned
                3'b101: mem[addr[11:2]] <= {16'b0, DataWr[15:0]};                // Halfword Unsigned
            endcase
        end
    end

endmodule

Monocycle/Verilog/Código/ALU.sv
module ALU (
  input [31:0] A,
  input [31:0] B,
  input [3:0] ALUOp,
  output reg [31:0] ALURes
);
  always @(*) begin
    case (ALUOp)
        4'b0000: ALURes = A + B;
      	4'b1000: ALURes = A - B;
      	4'b0001: ALURes = $signed(A) << $signed(B);
      	4'b0010: ALURes = $signed(A) < $signed(B);
      	4'b0011: ALURes = A < B;
      	4'b0100: ALURes = A ^ B;
      	4'b0101: ALURes = A >> B;
      	4'b1101: ALURes = A >>> B;
      	4'b0110: ALURes = A | B;
      	4'b0111: ALURes = A & B;
      	4'b1001: ALURes = A * B;
        default: ALURes = A;    
    endcase
  end
endmodule

Monocycle/Verilog/Código/immediate_generator.sv
module immediate_generator(
  	input wire [24:0] instruction,
    input wire [2:0] ImmSrc,
    output reg [31:0] imm_ext
);
     always @* begin
        case(ImmSrc)
            3'b000: begin
                imm_ext[11:0] = instruction[24:13];
                imm_ext[31:12] = {20{imm_ext[11]}};
            end
            3'b001: begin
                imm_ext[11:0] = {instruction[24:18], instruction[4:0]};
                imm_ext[31:12] = {20{imm_ext[11]}};
            end
            3'b010: begin
                imm_ext[20:0] = {instruction[24:5]};
                imm_ext[31:21] = {10{imm_ext[20]}};
            end
            3'b101: begin
                imm_ext[12:0] = {instruction[24], instruction[0], instruction[23:18], instruction[4:1], 1'b0};
                imm_ext[31:13] = {19{imm_ext[12]}};
            end
            3'b110: begin
                imm_ext[20:0] = {instruction[24], instruction[12:5], instruction[13], instruction[23:14], 1'b0};
                imm_ext[31:21] = {11{imm_ext[20]}};
            end
            default: imm_ext = 32'h0;
        endcase
    end

endmodule

Monocycle/Verilog/Código/control_unit.sv
module control_unit(
    input wire [6:0] OpCode,
  	input wire [2:0] funct3,
  	input wire [6:0] funct7,
    output reg [4:0] BrOp,
    output reg [2:0] DMCtrl,
    output reg DMWr,
    output reg [3:0] ALUOp,
    output reg ALUASrc,
    output reg ALUBSrc,
    output reg RUWr,
    output reg [1:0] RUDataWrSrc,
    output reg [2:0] ImmSrc
);

    always @(*) begin
    RUWr = 1'b0;
    ALUOp = 4'h0;
    ImmSrc = 3'h0;
    ALUASrc = 1'h0;
    ALUBSrc = 1'h0;
    DMWr = 1'h0;
    DMCtrl = 3'h0;
    BrOp = 5'h0;
    RUDataWrSrc = 2'h0;

    case (OpCode)
        7'b0110011: begin // R-Type instruction
   
          	if (funct7 == 7'b0000001 && funct3 == 3'b000) begin
          		ALUOp = 4'b1001; // Código para multiplicación entera
        	end 
          	else begin
            	ALUOp = {funct7[5], funct3[2:0]};
        	end
  
            RUWr = 1'b1;
            ALUASrc = 1'b0;
            ALUBSrc = 1'b0;
            ImmSrc = 3'bxxx;
            BrOp = 5'b00xxx;
            DMWr = 1'b0;
            DMCtrl = 3'bxxx;
            RUDataWrSrc = 2'b00;
        end
        7'b0010011: begin // I-Type instruction
            ALUOp = {1'b0, funct3};
            RUWr = 1'b1;
            ALUASrc = 1'b0;
            ALUBSrc = 1'b1;
            ImmSrc = 3'b000;
            BrOp = 5'b00xxx;
            DMWr = 1'b0;
            DMCtrl = 3'bxxx;
            RUDataWrSrc = 2'b00;
        end
        7'b0000011: begin // Load I-Type instruction
            ALUOp = 4'b0000;
            RUWr = 1'b1;
            ALUASrc = 1'b0;
            ALUBSrc = 1'b1;
            ImmSrc = 3'b000;
            BrOp = 5'b00xxx;
            DMWr = 1'b0;
            DMCtrl = funct3[2:0];
            RUDataWrSrc = 2'b01;
        end
        7'b0100011: begin // Store S-Type instruction
            ALUOp = 4'b0000;
            RUWr = 1'b0;
            ALUASrc = 1'b0;
            ALUBSrc = 1'b1;
            ImmSrc = 3'b001;
            BrOp = 5'b00xxx;
            DMWr = 1'b1;
            DMCtrl = funct3[2:0];
            RUDataWrSrc = 2'bxx;
        end
        7'b1100011: begin // Branch SB-Type instruction
            ALUOp = 4'b0000;
            RUWr = 1'b0;
            ALUASrc = 1'b1;
            ALUBSrc = 1'b1;
            ImmSrc = 3'b101;
            BrOp = {2'b01, funct3};
            DMWr = 1'b0;
            DMCtrl = 3'bxxx;
            RUDataWrSrc = 2'bxx;
        end
        7'b1101111: begin // Jal J-Type instruction
            ALUOp = 4'b0000;
            RUWr = 1'b1;
            ALUASrc = 1'b1;
            ALUBSrc = 1'b1;
            ImmSrc = 3'b110;
            BrOp = 5'b1xxxx;
            DMWr = 1'b0;
            DMCtrl = 3'bxxx;
            RUDataWrSrc = 2'b10;
        end
        7'b1100111: begin // Jalr I-Type instruction
            ALUOp = 4'b0000;
            RUWr = 1'b1;
            ALUASrc = 1'b0;
            ALUBSrc = 1'b1;
            ImmSrc = 3'b000;
            BrOp = 5'b1xxxx;
            DMWr = 1'b0;
            DMCtrl = 3'bxxx;
            RUDataWrSrc = 2'b10;
        end
        7'b0110111: begin // Lui U-Type instruction
            ALUOp = 4'b0000;
            RUWr = 1'b1;
            ALUASrc = 1'bx;
            ALUBSrc = 1'b1;
            ImmSrc = 3'b010;
            BrOp = 5'b00xxx;
            DMWr = 1'b0;
            DMCtrl = 3'bxxx;
            RUDataWrSrc = 2'b00;
        end
        7'b0010111: begin // Auipc U-Type instruction
            ALUOp = 4'b0000;
            RUWr = 1'b1;
            ALUASrc = 1'b1;
            ALUBSrc = 1'b1;
            ImmSrc = 3'b010;
            BrOp = 5'b00xxx;
            DMWr = 1'b0;
            DMCtrl = 3'bxxx;
            RUDataWrSrc = 2'b00;
        end
    endcase
end


endmodule

Monocycle/Verilog/Código/instruction_memory.sv
module instruction_memory(
    input wire [31:0] addr,
    output reg [31:0] instruction
);
    reg [7:0] mem [0:1023];
    
    initial begin
        $readmemh("instrucciones_verilog.hex", mem);
      	instruction = 32'b0;
    end
    
  always @(addr) begin

        instruction = {
            mem[addr], 
          	mem[addr+1],
          	mem[addr+2],
          	mem[addr+3]    
        };
    end
endmodule

Monocycle/Verilog/Código/PC.sv
module pc(
    input wire clk,
    input wire rst,
    input wire [31:0] pc_in,
    output reg [31:0] pc_out
);

    always @(posedge clk or posedge rst) begin
        if (rst)
            pc_out <= 32'h00000068;
        else
            pc_out <= pc_in;
    end
endmodule

Monocycle/Verilog/Código/design.sv
`include "ALU.sv"
`include "register_file.sv"
`include "data_memory.sv"
`include "instruction_memory.sv"
`include "PC.sv"
`include "control_unit.sv"
`include "immediate_generator.sv"
`include "branch_unit.sv"

module monocycle_processor (
    input wire clk,
    input wire rst
);

    wire [31:0] pc_out, pc_in, instruction, imm_ext;
    wire [31:0] RU_rs1, RU_rs2, ALURes, DataRd, DataWr;
    wire [4:0] rs1, rs2, rd;
    wire [2:0] funct3;
    wire [6:0] opcode, funct7;
    wire [4:0] BrOp;       
  	wire [3:0] ALUOp;
    wire DMWr, ALUASrc, ALUBSrc, RUWr;
    wire [1:0] RUDataWrSrc;
    wire [2:0] DMCtrl;
    wire [2:0] ImmSrc;
    wire NextPCSrc;
  

    pc PC (
        .clk(clk),
        .rst(rst),
        .pc_in(pc_in),
        .pc_out(pc_out)
    );

    instruction_memory IM (
        .addr(pc_out),
        .instruction(instruction)
    );

    assign opcode = instruction[6:0];
    assign funct3 = instruction[14:12];
    assign funct7 = instruction[31:25];
    assign rs1 = instruction[19:15];
    assign rs2 = instruction[24:20];
    assign rd = instruction[11:7];

    control_unit CU (
        .OpCode(opcode),
        .funct3(funct3),
        .funct7(funct7),
        .BrOp(BrOp),
        .DMCtrl(DMCtrl),
        .DMWr(DMWr),
        .ALUOp(ALUOp),
        .ALUASrc(ALUASrc),
        .ALUBSrc(ALUBSrc),
        .RUWr(RUWr),
        .RUDataWrSrc(RUDataWrSrc),
        .ImmSrc(ImmSrc)   
    );

    immediate_generator ImmGen (
      	.instruction(instruction[31:7]),
        .ImmSrc(ImmSrc),       
        .imm_ext(imm_ext)
    );
  
    // MUX para seleccionar ALU source A
    wire [31:0] ALUA = (ALUASrc) ? pc_out : RU_rs1;

    // MUX para seleccionar ALU source B
    wire [31:0] ALUB = (ALUBSrc) ? imm_ext : RU_rs2;

    ALU ALU (
        .A(ALUA),
        .B(ALUB),
        .ALUOp(ALUOp),         
        .ALURes(ALURes)
    );

    data_memory DM (
      	.clk(clk),
        .DMWr(DMWr),
        .DMCtrl(DMCtrl),
        .addr(ALURes),
        .DataWr(RU_rs2),
        .DataRd(DataRd)
    );
    
    branch_unit br_unit (
        .BrOp(BrOp),        
        .A(RU_rs1),
        .B(RU_rs2),
      	.NextPCSrc(NextPCSrc)
    );
  


    // Lógica para calcular el siguiente valor de PC
  	assign pc_in = (NextPCSrc) ? ALURes : pc_out + 4;

    // Lógica para seleccionar el valor de escritura en el registro
    assign DataWr = (RUDataWrSrc == 2'b00) ? ALURes :
                    (RUDataWrSrc == 2'b01) ? DataRd :
                    (RUDataWrSrc == 2'b10) ? (pc_out + 4) : 32'b0;
  
    register_file RF (
        .clk(clk),
        .rs1(rs1),
        .rs2(rs2),
        .rd(rd),
        .RUWr(RUWr),
        .DataWr(DataWr),
        .RU_rs1(RU_rs1),
        .RU_rs2(RU_rs2)
    );

endmodule

Monocycle/Verilog/Código/testbench.sv
`timescale 1ns/1ps

module monocycle_processor_tb();
    reg clk;
    reg rst;
    
    monocycle_processor cpu(
        .clk(clk),
        .rst(rst)
    );

    always begin
        clk = 0;
        #5; 
        clk = 1;
        #5;
    end

    integer file;

    task display_state;
        begin
            $fwrite(file, "Time=%0t ps\n", $time);
            $fwrite(file, "PC=%h\n", cpu.pc_out);
            $fwrite(file, "Instruction=%h\n", cpu.instruction);
            $fwrite(file, "Register File Status:\n");
            for (integer i = 0; i < 32; i = i + 1) begin
              if (cpu.RF.memory[i] != 0) begin
                $fwrite(file, "x%0d=%h\n", i, cpu.RF.memory[i]);
                end
            end
            $fwrite(file, "Memory Status:\n");
            for (integer i = 0; i < 64; i = i + 4) begin
                if (cpu.DM.mem[i/4] != 0) begin
                    $fwrite(file, "mem[%0h]=%h\n", i, cpu.DM.mem[i/4]);
                end
            end
            $fwrite(file, "-------------------------\n");
        end
    endtask
    

    initial begin
        file = $fopen("simulation_results.txt", "w");
        rst = 1;
        $readmemh("instrucciones_verilog.hex", cpu.IM.mem);
        #10;
        rst = 0;

      repeat(67) begin
            @(posedge clk);
            display_state();
        end
        
        $fclose(file);
        $finish;
    end

    initial begin
        $monitor("Time=%0t rst=%b pc=%h inst=%h",
                 $time, rst, cpu.pc_out, cpu.instruction);
    end
    
    initial begin
        $dumpfile("processor_waves.vcd");
        $dumpvars(0, monocycle_processor_tb);
    end
    
endmodule

Monocycle/Verilog/Código/processor_waves.vcd
$date
Wed Nov 20 18:18:54 2024
$end
$version
Riviera-PRO Version 2023.04.112.8911
$end
$timescale
1 ps
$end

$scope module monocycle_processor_tb $end
$var reg 1 ! clk $end
$var reg 1 " rst $end
$var integer 32 # file $end

$scope module cpu $end
$var wire 1 $ clk $end
$var wire 1 % rst $end
$var wire 32 & pc_out [31:0] $end
$var wire 32 ' pc_in [31:0] $end
$var wire 1 ( instruction [31] $end
$var wire 1 ) instruction [30] $end
$var wire 1 * instruction [29] $end
$var wire 1 + instruction [28] $end
$var wire 1 , instruction [27] $end
$var wire 1 - instruction [26] $end
$var wire 1 . instruction [25] $end
$var wire 1 / instruction [24] $end
$var wire 1 0 instruction [23] $end
$var wire 1 1 instruction [22] $end
$var wire 1 2 instruction [21] $end
$var wire 1 3 instruction [20] $end
$var wire 1 4 instruction [19] $end
$var wire 1 5 instruction [18] $end
$var wire 1 6 instruction [17] $end
$var wire 1 7 instruction [16] $end
$var wire 1 8 instruction [15] $end
$var wire 1 9 instruction [14] $end
$var wire 1 : instruction [13] $end
$var wire 1 ; instruction [12] $end
$var wire 1 < instruction [11] $end
$var wire 1 = instruction [10] $end
$var wire 1 > instruction [9] $end
$var wire 1 ? instruction [8] $end
$var wire 1 @ instruction [7] $end
$var wire 1 A instruction [6] $end
$var wire 1 B instruction [5] $end
$var wire 1 C instruction [4] $end
$var wire 1 D instruction [3] $end
$var wire 1 E instruction [2] $end
$var wire 1 F instruction [1] $end
$var wire 1 G instruction [0] $end
$var wire 32 H imm_ext [31:0] $end
$var wire 32 I RU_rs1 [31:0] $end
$var wire 32 J RU_rs2 [31:0] $end
$var wire 32 K ALURes [31:0] $end
$var wire 32 L DataRd [31:0] $end
$var wire 32 M DataWr [31:0] $end
$var wire 5 N rs1 [4:0] $end
$var wire 5 O rs2 [4:0] $end
$var wire 5 P rd [4:0] $end
$var wire 3 Q funct3 [2:0] $end
$var wire 7 R opcode [6:0] $end
$var wire 7 S funct7 [6:0] $end
$var wire 5 T BrOp [4:0] $end
$var wire 4 U ALUOp [3:0] $end
$var wire 1 V DMWr $end
$var wire 1 W ALUASrc $end
$var wire 1 X ALUBSrc $end
$var wire 1 Y RUWr $end
$var wire 2 Z RUDataWrSrc [1:0] $end
$var wire 3 [ DMCtrl [2:0] $end
$var wire 3 \ ImmSrc [2:0] $end
$var wire 1 ] NextPCSrc $end
$var wire 32 ^ ALUA [31:0] $end
$var wire 32 _ ALUB [31:0] $end

$scope module PC $end
$var wire 1 $ clk $end
$var wire 1 % rst $end
$var wire 32 ' pc_in [31:0] $end
$var reg 32 ` pc_out [31:0] $end
$upscope $end


$scope module IM $end
$var wire 32 & addr [31:0] $end
$var reg 32 a instruction [31:0] $end
$upscope $end


$scope module CU $end
$var wire 7 R OpCode [6:0] $end
$var wire 3 Q funct3 [2:0] $end
$var wire 7 S funct7 [6:0] $end
$var reg 5 b BrOp [4:0] $end
$var reg 3 c DMCtrl [2:0] $end
$var reg 1 d DMWr $end
$var reg 4 e ALUOp [3:0] $end
$var reg 1 f ALUASrc $end
$var reg 1 g ALUBSrc $end
$var reg 1 h RUWr $end
$var reg 2 i RUDataWrSrc [1:0] $end
$var reg 3 j ImmSrc [2:0] $end
$upscope $end


$scope module ImmGen $end
$var wire 1 ( instruction [24] $end
$var wire 1 ) instruction [23] $end
$var wire 1 * instruction [22] $end
$var wire 1 + instruction [21] $end
$var wire 1 , instruction [20] $end
$var wire 1 - instruction [19] $end
$var wire 1 . instruction [18] $end
$var wire 1 / instruction [17] $end
$var wire 1 0 instruction [16] $end
$var wire 1 1 instruction [15] $end
$var wire 1 2 instruction [14] $end
$var wire 1 3 instruction [13] $end
$var wire 1 4 instruction [12] $end
$var wire 1 5 instruction [11] $end
$var wire 1 6 instruction [10] $end
$var wire 1 7 instruction [9] $end
$var wire 1 8 instruction [8] $end
$var wire 1 9 instruction [7] $end
$var wire 1 : instruction [6] $end
$var wire 1 ; instruction [5] $end
$var wire 1 < instruction [4] $end
$var wire 1 = instruction [3] $end
$var wire 1 > instruction [2] $end
$var wire 1 ? instruction [1] $end
$var wire 1 @ instruction [0] $end
$var wire 3 \ ImmSrc [2:0] $end
$var reg 32 k imm_ext [31:0] $end
$upscope $end


$scope module ALU $end
$var wire 32 ^ A [31:0] $end
$var wire 32 _ B [31:0] $end
$var wire 4 U ALUOp [3:0] $end
$var reg 32 l ALURes [31:0] $end
$upscope $end


$scope module DM $end
$var wire 1 $ clk $end
$var wire 1 V DMWr $end
$var wire 3 [ DMCtrl [2:0] $end
$var wire 32 K addr [31:0] $end
$var wire 32 J DataWr [31:0] $end
$var reg 32 m DataRd [31:0] $end
$upscope $end


$scope module br_unit $end
$var wire 5 T BrOp [4:0] $end
$var wire 32 I A [31:0] $end
$var wire 32 J B [31:0] $end
$var reg 1 n NextPCSrc $end
$upscope $end


$scope module RF $end
$var wire 1 $ clk $end
$var wire 5 N rs1 [4:0] $end
$var wire 5 O rs2 [4:0] $end
$var wire 5 P rd [4:0] $end
$var wire 1 Y RUWr $end
$var wire 32 M DataWr [31:0] $end
$var wire 32 I RU_rs1 [31:0] $end
$var wire 32 J RU_rs2 [31:0] $end
$upscope $end

$upscope $end


$scope task display_state $end
$upscope $end

$upscope $end

$enddefinitions $end
$dumpvars
0!
1"
b10000000000000000000000000000011 #
0$
1%
b1101000 &
b1101100 '
1(
1)
1*
1+
1,
1-
1.
0/
00
01
02
03
04
05
06
17
08
09
0:
0;
0<
0=
0>
1?
0@
0A
0B
1C
0D
0E
1F
1G
b11111111111111111111111111100000 H
b10000000000 I
b0 J
b1111100000 K
bx L
b1111100000 M
b10 N
b0 O
b10 P
b0 Q
b10011 R
b1111111 S
b0xxx T
b0 U
0V
0W
1X
1Y
b0 Z
bx [
b0 \
0]
b10000000000 ^
b11111111111111111111111111100000 _
b1101000 `
b11111110000000010000000100010011 a
b0xxx b
bx c
0d
b0 e
0f
1g
1h
b0 i
b0 j
b11111111111111111111111111100000 k
b1111100000 l
bx m
0n
$end
#5000
1!
1$
b1111100000 I
b1111100000 ^
b1111000000 l
b1111000000 K
b1111000000 M
#10000
0"
0!
0$
0%
#15000
1!
1$
b1101100 `
b1111000000 I
b1101100 &
b1110000 '
b1111000000 ^
b100010010111000100011 a
b1110100000 l
b1110100000 K
0(
0)
0*
0+
0,
0-
0.
13
1:
1<
1=
1>
0?
1B
0C
b0 S
b1 O
b10 Q
b11100 P
b100011 R
b1110100000 M
b1101000 J
b1 k
0h
1g
b10 c
b0xxx b
b1 j
1d
bx i
bx Z
1V
b1 \
b10 [
0Y
b1 H
b1 _
bx M
b11100 k
b1111000001 l
b1111000001 K
b11100 H
b11100 _
b1111011100 l
b1111011100 K
#20000
0!
0$
#25000
1!
1$
b1110000 `
b1110000 &
b1110100 '
b100000010010110000100011 a
10
03
0>
b1000 O
b11000 P
b0 J
b11000 k
b11000 H
b11000 _
b1111011000 l
b1111011000 K
bx m
#30000
0!
0$
#35000
1!
1$
b1110100 `
b1110100 &
b1111000 '
b10000000010000010000010011 a
1.
00
0:
0<
0B
1C
b1 S
b0 O
b0 Q
b1000 P
b10011 R
b101000 k
b0 j
1g
0d
bx c
b0xxx b
b0 i
1h
1Y
b0 Z
bx [
0V
b0 \
b101000 H
b101000 _
b1111011000 M
b100000 k
b1111101000 l
b1111101000 K
b100000 H
b100000 _
b1111101000 M
b1111100000 l
b1111100000 K
b1111100000 M
b0 m
b0 L
#40000
0!
0$
#45000
1!
1$
b1111000 `
b1111000 &
b1111100 '
b10100000000011110010011 a
0.
11
13
07
1>
1?
1@
b0 S
b101 O
b0 N
b1111 P
b0 I
b0 ^
b101 k
1h
1g
bx c
b0xxx b
b100000 l
b100000 K
b101 H
b101 _
b100000 M
b101 l
b101 K
b101 M
#50000
0!
0$
#55000
1!
1$
b1111100 `
b1111100 &
b10000000 '
b11111110111101000010011000100011 a
1(
1)
1*
1+
1,
1-
1.
10
12
15
1:
0?
0@
1B
0C
b1111111 S
b1111 O
b1000 N
b10 Q
b1100 P
b100011 R
b1111100000 I
b101 J
b1111100000 ^
b11111111111111111111111111101111 k
0h
1g
b10 c
b0xxx b
b1 j
1d
bx i
b1111100101 l
b1111100101 K
bx Z
1V
b1 \
b10 [
0Y
b11111111111111111111111111101111 H
b11111111111111111111111111101111 _
b0xxxxx00x0x M
b11111111111111111111111111101100 k
b1111001111 l
b1111001111 K
b11111111111111111111111111101100 H
b11111111111111111111111111101100 _
b0xxxx00xxxx M
b1111001100 l
b1111001100 K
b0xxxx00xx00 M
bx m
bx L
bx M
#60000
0!
0$
#65000
1!
1$
b10000000 `
b10000000 &
b10000100 '
b11111110110001000010010100000011 a
02
03
0>
1?
0B
b1100 O
b1010 P
b11 R
b0 J
b11111111111111111111111111101010 k
b0 j
1g
0d
b10 c
b0xxx b
b1 i
1h
1Y
b1 Z
0V
b0 \
b11111111111111111111111111101010 H
b11111111111111111111111111101010 _
b11111111111111111111111111101100 k
b1111001010 l
b1111001010 K
b11111111111111111111111111101100 H
b11111111111111111111111111101100 _
b1111001100 l
b1111001100 K
b101 m
b101 L
b101 M
#70000
0!
0$
#75000
1!
1$
b10000100 `
b10000100 &
b10001000 '
b11110111110111111111000011101111 a
0,
1/
13
14
16
17
18
19
1;
0=
0?
1@
1A
1B
1D
1E
b1111011 S
b11101 O
b11111 N
b111 Q
b1 P
b1101111 R
b0 I
b0 ^
b11111111111111111111111101111101 k
1h
1g
bx c
b1xxxx b
b10 i
1f
b110 j
b11111111111111111111111111101100 l
b11111111111111111111111111101100 K
b110 \
1W
b10 Z
b1xxxx T
bx [
b11111111111111111111111101111101 H
b11111111111111111111111101111101 _
b10001000 M
b10000100 ^
b11111111111111111111111101111100 k
1n
b1 l
b1 K
1]
b11111111111111111111111101111100 H
b11111111111111111111111101111100 _
b1 '
b0 l
b0 K
b0 '
#80000
0!
0$
#85000
1!
1$
b0 `
b0 &
b100 M
b0 ^
b11111101000000010000000100010011 a
b11111111111111111111111101111100 l
b11111111111111111111111101111100 K
1,
0.
00
01
03
04
05
06
08
09
0:
0;
1?
0@
0A
0B
1C
0D
0E
b1111110 S
b10000 O
b10 N
b0 Q
b10 P
b10011 R
b11111111111111111111111101111100 '
b1111000000 I
b11111111111100010000011111010000 k
1h
b0 j
0f
1g
bx c
b0xxx b
b0 i
b0 Z
b0xxx T
0W
b0 \
b11111111111100010000011111010000 H
b11111111111100010000011111010000 _
b1111000000 ^
b11111111111111111111111101111100 M
0n
b11111111111111111111111111010000 k
b11111111111100010000101110010000 l
b11111111111100010000101110010000 K
b11111111111111111111111111010000 H
0]
b11111111111111111111111111010000 _
b11111111111100010000101110010000 M
b100 '
b1110010000 l
b1110010000 K
b1110010000 M
#90000
0!
0$
#95000
1!
1$
b100 `
b1110010000 I
b100 &
b1000 '
b1110010000 ^
b10000100010010011000100011 a
b1101100000 l
b1101100000 K
0(
0)
0*
0+
0,
0-
1.
0/
13
1:
1=
1>
0?
1B
0C
b1 S
b1 O
b10 Q
b1100 P
b100011 R
b1101100000 M
b10001000 J
b100001 k
0h
1g
b10 c
b0xxx b
b1 j
1d
bx i
bx Z
1V
b1 \
b10 [
0Y
b100001 H
b100001 _
b0xx0xx0xx0x M
b101100 k
b1110110001 l
b1110110001 K
b101100 H
b101100 _
b0xxx0xxxx0x M
b1110111100 l
b1110111100 K
bx m
bx L
bx M
#100000
0!
0$
#105000
1!
1$
b1000 `
b1000 &
b1100 '
b10100000010010010000100011 a
10
03
0>
b1000 O
b1000 P
b1111100000 J
b101000 k
b101000 H
b101000 _
b1110111000 l
b1110111000 K
bx m
#110000
0!
0$
#115000
1!
1$
b1100 `
b1100 &
b10000 '
b11000000010000010000010011 a
1/
00
0:
0B
1C
b10000 O
b0 Q
b10011 R
b0 J
b0 j
1g
0d
bx c
b0xxx b
b0 i
1h
1Y
b0 Z
bx [
0V
b0 \
b1110111000 M
b110000 k
b110000 H
b110000 _
b1111000000 l
b1111000000 K
b1111000000 M
b1111100000 m
b1111100000 L
#120000
0!
0$
#125000
1!
1$
b10000 `
b10000 &
b10100 '
b11111100101001000010111000100011 a
1(
1)
1*
1+
1,
1-
0.
0/
10
12
15
07
1:
1<
1>
1B
0C
b1111110 S
b1010 O
b1000 N
b10 Q
b11100 P
b100011 R
b1111000000 I
b101 J
b1111000000 ^
b11111111111111111111111111001010 k
0h
1g
b10 c
b0xxx b
b1 j
1d
bx i
b1111110000 l
b1111110000 K
bx Z
1V
b1 \
b10 [
0Y
b11111111111111111111111111001010 H
b11111111111111111111111111001010 _
b0xxxxxx0x00 M
b11111111111111111111111111011100 k
b1110001010 l
b1110001010 K
b11111111111111111111111111011100 H
b11111111111111111111111111011100 _
b0xxxxxxxxx0 M
b1110011100 l
b1110011100 K
b0xxxxxxxx00 M
bx m
bx L
bx M
#130000
0!
0$
#135000
1!
1$
b10100 `
b10100 &
b11000 '
b100000000011110010011 a
0(
0)
0*
0+
0,
0-
00
02
13
05
0:
0<
1?
1@
0B
1C
b0 S
b1 O
b0 N
b0 Q
b1111 P
b10011 R
b0 I
b10001000 J
b0 ^
b1111 k
b0 j
1g
0d
bx c
b0xxx b
b0 i
1h
b11111111111111111111111111011100 l
b11111111111111111111111111011100 K
1Y
b0 Z
bx [
0V
b0 \
b1111 H
b1111 _
b11111111111111111111111111011100 M
b1 k
b1111 l
b1111 K
b1 H
b1 _
b1111 M
b1 l
b1 K
b1 M
b101 m
b101 L
#140000
0!
0$
#145000
1!
1$
b11000 `
b11000 &
b11100 '
b11111110111101000010011000100011 a
1(
1)
1*
1+
1,
1-
1.
10
11
12
15
1:
0?
0@
1B
0C
b1111111 S
b1111 O
b1000 N
b10 Q
b1100 P
b100011 R
b1111000000 I
b1 J
b1111000000 ^
b11111111111111111111111111101111 k
0h
1g
b10 c
b0xxx b
b1 j
1d
bx i
b1111000001 l
b1111000001 K
bx Z
1V
b1 \
b10 [
0Y
b11111111111111111111111111101111 H
b11111111111111111111111111101111 _
b0xxxx0xxx0x M
b11111111111111111111111111101100 k
b1110101111 l
b1110101111 K
b11111111111111111111111111101100 H
b11111111111111111111111111101100 _
b0xxx0xxxxxx M
b1110101100 l
b1110101100 K
b0xxx0xxxx0x M
bx m
bx L
bx M
#150000
0!
0$
#155000
1!
1$
b11100 `
b11100 &
b100000 '
b1000000000011110010011 a
0(
0)
0*
0+
0,
0-
0.
00
01
03
05
0:
1?
1@
0B
1C
b0 S
b10 O
b0 N
b0 Q
b1111 P
b10011 R
b0 I
b1110010000 J
b0 ^
b1111 k
b0 j
1g
0d
bx c
b0xxx b
b0 i
1h
b11111111111111111111111111101100 l
b11111111111111111111111111101100 K
1Y
b0 Z
bx [
0V
b0 \
b1111 H
b1111 _
b11111111111111111111111111101100 M
b10 k
b1111 l
b1111 K
b10 H
b10 _
b1111 M
b10 l
b10 K
b10 M
b1 m
b1 L
#160000
0!
0$
#165000
1!
1$
b100000 `
b100000 &
b100100 '
b11111110111101000010010000100011 a
1(
1)
1*
1+
1,
1-
1.
10
11
13
15
1:
0>
0?
0@
1B
0C
b1111111 S
b1111 O
b1000 N
b10 Q
b1000 P
b100011 R
b1111000000 I
b10 J
b1111000000 ^
b11111111111111111111111111101111 k
0h
1g
b10 c
b0xxx b
b1 j
1d
bx i
b1111000010 l
b1111000010 K
bx Z
1V
b1 \
b10 [
0Y
b11111111111111111111111111101111 H
b11111111111111111111111111101111 _
b0xxxxx00xxx M
b11111111111111111111111111101000 k
b1110101111 l
b1110101111 K
b11111111111111111111111111101000 H
b11111111111111111111111111101000 _
b0xxx0x0xxxx M
b1110101000 l
b1110101000 K
b0xxx0x0xx0x M
bx m
bx L
bx M
#170000
0!
0$
#175000
1!
1$
b100100 `
b100100 &
b101000 '
b10000000000000000001101111 a
0(
0)
0*
0+
0,
0-
00
01
02
03
05
0:
0=
1A
1D
1E
b1 S
b0 O
b0 N
b0 Q
b0 P
b1101111 R
b0 I
b0 J
b0 ^
b100000 k
b110 j
1g
0d
bx c
b1xxxx b
b10 i
1h
1f
b11111111111111111111111111101000 l
b11111111111111111111111111101000 K
1W
1Y
b10 Z
b1xxxx T
bx [
0V
b110 \
b100000 H
b100000 _
b100100 ^
b101000 M
1n
b1000100 l
b1000100 K
1]
b1000100 '
b10 m
b10 L
#180000
0!
0$
